serializer/__init__.py
serializer/custom.py
serializer/main.py
serializer/src/__init__.py
serializer/src/constants.py
serializer/src/converter.py
serializer/src/factory.py
serializer/src/json_serializer.py
serializer/src/supportive.py
serializer/src/xml_serializer.py
Ma3serializer-1.0.0.dist-info/METADATA
Ma3serializer-1.0.0.dist-info/WHEEL
Ma3serializer-1.0.0.dist-info/top_level.txt
Ma3serializer-1.0.0.dist-info/RECORD
