Metadata-Version: 2.1
Name: Ma3serializer
Version: 1.0.0
Summary: JSON/XML serializer
Author: Ma3yTuK
Author-email: nazarmatveev2003@gmail.com
